tongWnB/__init__.py
tongWnB/export.py
tongWnB/package.json
tongWnB/swan.py
tongwnb-1.0.1.dist-info/METADATA
tongwnb-1.0.1.dist-info/WHEEL
tongwnb-1.0.1.dist-info/licenses/LICENSE
tongwnb-1.0.1.dist-info/RECORD
