Metadata-Version: 2.4
Name: tongWnB
Version: 1.0.1
Summary: Python library for streamlined tracking and management of AI training processes.
Project-URL: Homepage, https://github.com/tong-gpu-monitor/tongWnB
Project-URL: Repository, https://github.com/tong-gpu-monitor/tongWnB
Author-email: TongWnB <yangcan@tongtech.com>
License-Expression: MIT
License-File: LICENSE
Requires-Python: >=3.10
Requires-Dist: requests>=2.25.0
Provides-Extra: test
Requires-Dist: pytest-cov>=4.0.0; extra == 'test'
Requires-Dist: pytest>=7.0.0; extra == 'test'
